appyter/__init__.py
appyter/__main__.py
appyter/cli.py
appyter/context.py
appyter/execspec/__init__.py
appyter/execspec/core.py
appyter/execspec/implementations/__init__.py
appyter/execspec/implementations/cavatica.py
appyter/execspec/implementations/dispatch.py
appyter/execspec/implementations/docker.py
appyter/execspec/implementations/kube.py
appyter/execspec/implementations/local.py
appyter/execspec/implementations/subprocess.py
appyter/execspec/implementations/wes.py
appyter/execspec/registry.py
appyter/execspec/spec.py
appyter/ext/__init__.py
appyter/ext/aiohttp.py
appyter/ext/asyncio/__init__.py
appyter/ext/asyncio/event_emitter.py
appyter/ext/asyncio/event_loop.py
appyter/ext/asyncio/helpers.py
appyter/ext/asyncio/subprocess.py
appyter/ext/asyncio/test_helpers.py
appyter/ext/asyncio/test_subprocess.py
appyter/ext/asyncio/try_n_times.py
appyter/ext/click/__init__.py
appyter/ext/contextlib.py
appyter/ext/cryptography.py
appyter/ext/dict.py
appyter/ext/drs.py
appyter/ext/emitter.py
appyter/ext/exceptions.py
appyter/ext/flask.py
appyter/ext/fsspec/__init__.py
appyter/ext/fsspec/chroot.py
appyter/ext/fsspec/core.py
appyter/ext/fsspec/drs.py
appyter/ext/fsspec/fuse.py
appyter/ext/fsspec/mapperfs.py
appyter/ext/fsspec/overlayfs.py
appyter/ext/fsspec/s3fs.py
appyter/ext/fsspec/sbfs.py
appyter/ext/fsspec/singleton.py
appyter/ext/fsspec/spec/__init__.py
appyter/ext/fsspec/spec/composable.py
appyter/ext/fsspec/spec/mountable.py
appyter/ext/fsspec/spec/sync_async.py
appyter/ext/fsspec/storage.py
appyter/ext/fsspec/test_chroot.py
appyter/ext/fsspec/test_drs.py
appyter/ext/fsspec/test_fuse.py
appyter/ext/fsspec/test_fuseless_mount.py
appyter/ext/fsspec/test_mapperfs.py
appyter/ext/fsspec/test_overlayfs.py
appyter/ext/fsspec/test_pathmap.py
appyter/ext/fsspec/test_sbfs.py
appyter/ext/fsspec/util.py
appyter/ext/fsspec/writecache.py
appyter/ext/functools.py
appyter/ext/hashlib.py
appyter/ext/importlib.py
appyter/ext/io.py
appyter/ext/itertools.py
appyter/ext/json.py
appyter-0.21.7.dist-info/LICENSE
appyter-0.21.7.dist-info/METADATA
appyter-0.21.7.dist-info/WHEEL
appyter-0.21.7.dist-info/entry_points.txt
appyter-0.21.7.dist-info/RECORD
