Metadata-Version: 2.3
Name: appyter
Version: 0.21.7
Summary: This module enables you to turn your jupyter notebook into a jinja2 template-driven web application.
License: CC-BY-NC-SA-4.0
Author: Daniel Clarke
Author-email: u8sand@gmail.com
Requires-Python: >=3.9
Classifier: Development Status :: 4 - Beta
Classifier: Operating System :: OS Independent
Classifier: Programming Language :: Python :: 3.7
Classifier: Programming Language :: Python :: 3
Classifier: Topic :: Scientific/Engineering
Classifier: Topic :: Software Development :: Libraries :: Application Frameworks
Classifier: Framework :: Jupyter
Provides-Extra: appyter-init
Provides-Extra: doc
Provides-Extra: docs
Provides-Extra: production
Requires-Dist: aiobotocore (>=2.23.0,<3.0.0) ; extra == "production"
Requires-Dist: aiohttp (>=3.12.13,<4.0.0)
Requires-Dist: aiohttp-remotes (>=1.3.0,<2.0.0)
Requires-Dist: aiohttp-wsgi (>=0.10.0,<0.11.0)
Requires-Dist: bs4 (>=0.0.2,<0.0.3)
Requires-Dist: click (<8.2)
Requires-Dist: click-default-group (>=1.2.4,<2.0.0)
Requires-Dist: cookiecutter (>=2.6.0,<3.0.0) ; extra == "appyter-init"
Requires-Dist: flask (>=3.1.1,<4.0.0)
Requires-Dist: flask-cors (<6)
Requires-Dist: fsspec (>=2025.5.1,<2026.0.0)
Requires-Dist: fusepy (>=3.0.1,<4.0.0)
Requires-Dist: ipython (<9.3)
Requires-Dist: jinja2 (>=3.1.6,<4.0.0)
Requires-Dist: jupyter-client (>=8.6.3,<9.0.0)
Requires-Dist: kubernetes (>=33.1.0,<34.0.0) ; extra == "production"
Requires-Dist: lxml (>=5.4.0,<6.0.0)
Requires-Dist: nbclient (>=0.10.2,<0.11.0)
Requires-Dist: nbconvert (>=7.16.6,<8.0.0)
Requires-Dist: nbformat (>=5.10.4,<6.0.0)
Requires-Dist: notebook (>=7.4.3,<8.0.0)
Requires-Dist: python-dotenv (>=1.1.1,<2.0.0)
Requires-Dist: python-engineio (>=4.12.2,<5.0.0)
Requires-Dist: python-socketio (>=5.13.0,<6.0.0)
Requires-Dist: pyyaml (>=6.0.2,<7.0.0)
Requires-Dist: s3fs (>=2025.5.1,<2026.0.0) ; extra == "production"
Requires-Dist: sphinx (<8) ; extra == "docs"
Requires-Dist: sphinx-mdinclude (<0.6.2) ; extra == "docs"
Requires-Dist: supervisor (>=4.2.5,<5.0.0) ; extra == "production"
Requires-Dist: watchgod (>=0.8.2,<0.9.0)
Requires-Dist: werkzeug (>=3.1.3,<4.0.0)
Requires-Dist: yarl (>=1.20.1,<2.0.0)
